Metadata-Version: 1.0
Name: cstore-api
Version: 0.3
Summary: Korean CStore API
Home-page: https://github.com/DSMdongly/Caspi
Author: Toygrammer
Author-email: gdh0608@naver.com
License: MIT
Platform: UNKNOWN
